tof/__init__.py
tof/chopper.py
tof/dashboard.py
tof/deprecation.py
tof/detector.py
tof/model.py
tof/py.typed
tof/reading.py
tof/result.py
tof/source.py
tof/utils.py
tof/facilities/__init__.py
tof/facilities/ess/__init__.py
tof/facilities/ess/dream.py
tof/facilities/ess/odin.py
tof/facilities/ess_pulse/__init__.py
tof/facilities/ess_pulse/pulse_profile.py
tof-25.12.1.dist-info/licenses/LICENSE
tof-25.12.1.dist-info/METADATA
tof-25.12.1.dist-info/WHEEL
tof-25.12.1.dist-info/top_level.txt
tof-25.12.1.dist-info/RECORD
