Metadata-Version: 2.4
Name: tof
Version: 25.12.1
Summary: A simple tool to create time-of-flight chopper cascade diagrams
Author: Scipp contributors
License-Expression: BSD-3-Clause
Project-URL: Bug Tracker, https://github.com/scipp/tof/issues
Project-URL: Documentation, https://scipp.github.io/tof
Project-URL: Source, https://github.com/scipp/tof
Classifier: Intended Audience :: Science/Research
Classifier: Natural Language :: English
Classifier: Operating System :: OS Independent
Classifier: Programming Language :: Python :: 3
Classifier: Programming Language :: Python :: 3 :: Only
Classifier: Programming Language :: Python :: 3.11
Classifier: Programming Language :: Python :: 3.12
Classifier: Programming Language :: Python :: 3.13
Classifier: Topic :: Scientific/Engineering
Classifier: Typing :: Typed
Requires-Python: >=3.11
License-File: LICENSE
Requires-Dist: plopp>=23.10.0
Requires-Dist: pooch>=1.5.0
Requires-Dist: scipp>=24.11.0
Requires-Dist: lazy-loader>=0.3
Provides-Extra: test
Requires-Dist: pytest>=8.0; extra == "test"
Requires-Dist: scippneutron>=24.12.0; extra == "test"
Dynamic: license-file
